setup.py
bin/ptsd
ptsd/__init__.py
ptsd/ast.py
ptsd/constants.py
ptsd/lexer.py
ptsd/loader.py
ptsd/parser.py
ptsd.egg-info/PKG-INFO
ptsd.egg-info/SOURCES.txt
ptsd.egg-info/dependency_links.txt
ptsd.egg-info/requires.txt
ptsd.egg-info/top_level.txt
ptsd.egg-info/zip-safe