Metadata-Version: 1.0
Name: ptsd
Version: 0.1.0
Summary: python thrift simple/dumb
Home-page: http://github.com/wickman/ptsd
Author: Brian Wickman
Author-email: wickman@gmail.com
License: UNKNOWN
Platform: UNKNOWN
